mia_anemoi/__init__.py
mia_anemoi/client.py
mia_anemoi/messages.py
mia_anemoi/transport.py
mia_anemoi-0.1.0.dist-info/METADATA
mia_anemoi-0.1.0.dist-info/WHEEL
mia_anemoi-0.1.0.dist-info/top_level.txt
mia_anemoi-0.1.0.dist-info/RECORD
