Metadata-Version: 2.4
Name: mia-anemoi
Version: 0.1.0
Summary: Agent-to-Agent Communication Library - Mia's fork of Coral-Protocol/Anemoi
Author-email: Mia Isabelle <mia@example.com>
Maintainer-email: Mia Isabelle <mia@example.com>
License: MIT
Project-URL: Homepage, https://github.com/miadisabelle/mia-anemoi
Project-URL: Documentation, https://github.com/miadisabelle/mia-anemoi#readme
Project-URL: Repository, https://github.com/miadisabelle/mia-anemoi.git
Project-URL: Issues, https://github.com/miadisabelle/mia-anemoi/issues
Keywords: anemoi,a2a,agent,mcp,ai,communication
Classifier: Development Status :: 3 - Alpha
Classifier: Intended Audience :: Developers
Classifier: License :: OSI Approved :: MIT License
Classifier: Operating System :: OS Independent
Classifier: Programming Language :: Python :: 3
Classifier: Programming Language :: Python :: 3.10
Classifier: Programming Language :: Python :: 3.11
Classifier: Programming Language :: Python :: 3.12
Classifier: Topic :: Software Development :: Libraries :: Python Modules
Classifier: Topic :: Communications
Requires-Python: >=3.10
Requires-Dist: pyyaml>=6.0
Provides-Extra: dev
Requires-Dist: pytest>=7.0; extra == "dev"
Requires-Dist: pytest-asyncio>=0.21; extra == "dev"
Requires-Dist: black>=23.0; extra == "dev"
Requires-Dist: isort>=5.0; extra == "dev"
Requires-Dist: mypy>=1.0; extra == "dev"
Requires-Dist: build>=1.0; extra == "dev"
Requires-Dist: twine>=4.0; extra == "dev"
Provides-Extra: mcp
Requires-Dist: mcp>=1.0; extra == "mcp"
Requires-Dist: httpx>=0.24; extra == "mcp"
Requires-Dist: httpx-sse>=0.4; extra == "mcp"
Provides-Extra: agents
Requires-Dist: aiohttp>=3.12.9; extra == "agents"
Requires-Dist: camel-ai[all]==0.2.70; extra == "agents"
Requires-Dist: docx2markdown>=0.1.1; extra == "agents"
Requires-Dist: httpx-sse>=0.4.0; extra == "agents"
Requires-Dist: loguru>=0.7.3; extra == "agents"
Requires-Dist: mcp==1.10.1; extra == "agents"
Requires-Dist: opencv-python>=4.11.0.86; extra == "agents"
Requires-Dist: python-dotenv>=1.1.1; extra == "agents"
Requires-Dist: retry>=0.9.2; extra == "agents"
Requires-Dist: starlette>=0.47.0; extra == "agents"
Requires-Dist: tqdm>=4.67.1; extra == "agents"
Requires-Dist: yarl>=1.20.0; extra == "agents"
Provides-Extra: all
Requires-Dist: mia-anemoi[agents,dev,mcp]; extra == "all"
